{
  "recentFiles": [
    {
      "basename": "marriage certificate",
      "path": "_inbox/marriage certificate.md"
    },
    {
      "basename": "0010_Miscalenous",
      "path": "0010_Miscalenous.md"
    },
    {
      "basename": "002_microservices MOC",
      "path": "002_microservices MOC.md"
    },
    {
      "basename": "everything i wants to do",
      "path": "everything i wants to do.md"
    },
    {
      "basename": "How to Become a Better Software Engineer",
      "path": "How to Become a Better Software Engineer.md"
    },
    {
      "basename": "0012 HydroElectric",
      "path": "0012 HydroElectric.md"
    },
    {
      "basename": "0011 In Progress",
      "path": "0011 In Progress.md"
    },
    {
      "basename": "Streaming in java",
      "path": "_inbox/Streaming in java.md"
    },
    {
      "basename": "goa",
      "path": "_inbox/goa.md"
    },
    {
      "basename": "SWP",
      "path": "_inbox/SWP.md"
    },
    {
      "basename": "Tek System",
      "path": "_inbox/Tek System.md"
    },
    {
      "basename": "Finance",
      "path": "_inbox/Finance/Finance.md"
    },
    {
      "basename": "googleKeep Notes",
      "path": "_inbox/googleKeep Notes.md"
    },
    {
      "basename": "home loan",
      "path": "_inbox/home loan.md"
    },
    {
      "basename": "Sango life sutras",
      "path": "_inbox/Sango life sutras.md"
    },
    {
      "basename": "003_productivity MOC",
      "path": "003_productivity MOC.md"
    },
    {
      "basename": "11 Tips for healthy sperm",
      "path": "_inbox/11 Tips for healthy sperm.md"
    },
    {
      "basename": "how to buy phone in sale",
      "path": "_inbox/how to buy phone in sale.md"
    },
    {
      "basename": "everything about insurance",
      "path": "_inbox/everything about insurance.md"
    },
    {
      "basename": "005_Project Ideas MOC",
      "path": "005_Project Ideas MOC.md"
    },
    {
      "basename": "007_Challenges",
      "path": "007_Challenges.md"
    },
    {
      "basename": "money",
      "path": "_inbox/money.md"
    },
    {
      "basename": "how to save money on tax",
      "path": "_inbox/Finance/how to save money on tax.md"
    },
    {
      "basename": "wardrobe for home",
      "path": "_inbox/wardrobe for home.md"
    },
    {
      "basename": "Priyu birthday video",
      "path": "_inbox/Priyu birthday video.md"
    },
    {
      "basename": "how to become nutritionist",
      "path": "_inbox/how to become nutritionist.md"
    },
    {
      "basename": "DIY cleaners",
      "path": "_inbox/DIY cleaners.md"
    },
    {
      "basename": "courses that you can do to earn more",
      "path": "_inbox/courses that you can do to earn more.md"
    },
    {
      "basename": "caring less about job we can get what we want",
      "path": "_inbox/caring less about job we can get what we want.md"
    },
    {
      "basename": "build wealth rich gilbert",
      "path": "_inbox/build wealth rich gilbert.md"
    },
    {
      "basename": "Productivity",
      "path": "_inbox/Productivity/Productivity.md"
    },
    {
      "basename": "cancel maxlife insurance policy",
      "path": "_inbox/cancel maxlife insurance policy.md"
    },
    {
      "basename": "44 cheatcodes for 44 years",
      "path": "_inbox/44 cheatcodes for 44 years.md"
    },
    {
      "basename": "Bike and Car Service Updates",
      "path": "_inbox/Bike and Car Service Updates.md"
    },
    {
      "basename": "what to do after work",
      "path": "_inbox/what to do after work.md"
    },
    {
      "basename": "7 years of software engineering advice",
      "path": "_inbox/7 years of software engineering advice.md"
    },
    {
      "basename": "FIRE",
      "path": "_inbox/FIRE.md"
    },
    {
      "basename": "001_interviews MOC",
      "path": "001_interviews MOC.md"
    },
    {
      "basename": "Remote job",
      "path": "_inbox/JOB-Hunt/companies/Remote job.md"
    },
    {
      "basename": "how to think like a developer",
      "path": "_inbox/how to think like a developer.md"
    },
    {
      "basename": "how to learn faster",
      "path": "_inbox/how to learn faster.md"
    },
    {
      "basename": "004_philosphy MOC",
      "path": "004_philosphy MOC.md"
    },
    {
      "basename": "Car Service Checklist",
      "path": "_inbox/Car Service Checklist.md"
    },
    {
      "basename": "hsbc onboarding details",
      "path": "_inbox/hsbc onboarding details.md"
    },
    {
      "basename": "Multithreading and multiprocessing",
      "path": "_inbox/JOB-Hunt/Interview-Questions-Solutions/Multithreading and multiprocessing.md"
    },
    {
      "basename": "40 lessons for a developer",
      "path": "_inbox/40 lessons for a developer.md"
    },
    {
      "basename": "what is @Configuration and @ConfigurationProperties",
      "path": "_inbox/what is @Configuration and @ConfigurationProperties.md"
    },
    {
      "basename": "spring boot interview questions",
      "path": "_inbox/fleeting/spring boot interview questions.md"
    },
    {
      "basename": "interview-experiences",
      "path": "_inbox/interview-experiences.md"
    },
    {
      "basename": "Untitled",
      "path": "Untitled.canvas"
    }
  ],
  "omittedPaths": [],
  "maxLength": null,
  "openType": "tab"
}